agent/__init__.py
agent/client.py
agent/exceptions.py
agent/services/__init__.py
agent/services/anomaly_alert.py
agent/services/audit_report.py
agent/services/data_storage.py
agent/services/motor_telemetry.py
agent/services/sensor_data.py
agent/services/system_logs.py
agent_client_hufr-1.0.0.dist-info/LICENSE
agent_client_hufr-1.0.0.dist-info/METADATA
agent_client_hufr-1.0.0.dist-info/WHEEL
agent_client_hufr-1.0.0.dist-info/top_level.txt
agent_client_hufr-1.0.0.dist-info/RECORD
