Metadata-Version: 2.1
Name: agent-client-hufr
Version: 1.0.0
Summary: A Python client library for communicating with the Flask server
Home-page: https://github.com/TahaW863/agent-client
Author: Taha
Author-email: tghara1@lsu.edu
License: UNKNOWN
Platform: UNKNOWN
Classifier: Programming Language :: Python :: 3
Classifier: License :: OSI Approved :: MIT License
Classifier: Operating System :: OS Independent
Requires-Python: >=3.6
License-File: LICENSE
Requires-Dist: requests
